Metadata-Version: 2.1
Name: emotext
Version: 0.1
Summary: emotext is a python package created for analyze sentiment it can be negative, neutral or positive
Home-page: https://github.com/rizki4106/emotext
Author: Rizki Maulana
Author-email: rizkimaulana348@gmail.com
License: MIT
Download-URL: https://github.com/rizki4106/emotext/archive/v_01.tar.gz
Keywords: sentiment,analysis,machine-learning
Platform: UNKNOWN
Classifier: Development Status :: 3 - Alpha
Classifier: Intended Audience :: Developers
Classifier: Topic :: Software Development :: Build Tools
Classifier: License :: OSI Approved :: MIT License
Classifier: Programming Language :: Python :: 3
